{"name":"Manga downloader","tagline":"","body":"### Добро пожаловать.\r\nПрограмма MangaReader предназначена для скачивания манги с онлайн читалок.\r\n\r\nПоддерживает скачивание манги целиком или обновление с последнего запуска манги.\r\n\r\n### Авторы и прочая\r\nMonk Alex (@monkalex)\r\n\r\n### Поддержка\r\nМожно писать на [email](mailto:monk@citydom.ru) или [оформлять баги](https://github.com/MonkAlex/MangaReader/issues)","google":"","note":"Don't delete this file! It's used internally to help with page regeneration."}
